vikunja_mcp/__init__.py
vikunja_mcp/server.py
vikunja_mcp-0.7.1.dist-info/METADATA
vikunja_mcp-0.7.1.dist-info/WHEEL
vikunja_mcp-0.7.1.dist-info/entry_points.txt
vikunja_mcp-0.7.1.dist-info/licenses/LICENSE
vikunja_mcp-0.7.1.dist-info/RECORD
