Metadata-Version: 2.4
Name: vikunja-mcp
Version: 0.7.1
Summary: MCP server for Vikunja task management
Project-URL: Homepage, https://pypi.org/project/vikunja-mcp/
Project-URL: Repository, https://github.com/ivantohelpyou/vikunja-mcp
Project-URL: Issues, https://github.com/ivantohelpyou/vikunja-mcp/issues
Author-email: Ivan Schneider <ivan@ivantohelpyou.com>
License: MIT
License-File: LICENSE
Keywords: ai,claude,mcp,task-management,vikunja
Classifier: Development Status :: 4 - Beta
Classifier: Intended Audience :: Developers
Classifier: License :: OSI Approved :: MIT License
Classifier: Programming Language :: Python :: 3
Classifier: Programming Language :: Python :: 3.10
Classifier: Programming Language :: Python :: 3.11
Classifier: Programming Language :: Python :: 3.12
Classifier: Topic :: Software Development :: Libraries :: Python Modules
Requires-Python: >=3.10
Requires-Dist: fastmcp>=0.4.0
Requires-Dist: pydantic>=2.0
Requires-Dist: requests>=2.31.0
Provides-Extra: dev
Requires-Dist: pytest-asyncio>=0.21; extra == 'dev'
Requires-Dist: pytest>=7.0; extra == 'dev'
